rc4/rc4.v
`define KEY_SIZE 7
module rc4(clk,rst,output_ready,password_input,K, init_done, valid);

input clk; // Clock
input rst; // Reset
input [7:0] password_input; // Password input
output output_ready; // Output valid
output [7:0] K; // Output port
   input     valid;
   

wire clk, rst; // clock, reset
reg output_ready;
wire [7:0] password_input;
output wire    init_done;
input wire  start;
   
   

/* RC4 PRGA */

// Key
reg [7:0] key;
// S array
reg [7:0] S[0:256];
reg [9:0] discardCount;

// Key-scheduling state
`define KSS_KEYREAD 4'h0
`define KSS_KEYSCHED1 4'h1
`define KSS_KEYSCHED2 4'h2
`define KSS_KEYSCHED3 4'h3
`define KSS_CRYPTO 	 4'h4
`define KSS_CRYPTO2 	 4'h5
`define RST_STATE 4'h6
`define RDY_STATE 4'h7
`define DONE_STATE 4'h8
   
// Variable names from http://en.wikipedia.org/wiki/RC4
   reg [3:0] KSState;
reg [7:0] i; // Counter
reg [7:0] j;
reg [7:0] K;
   reg [7:0] temp_K;
   
reg [7:0] tmp;

always @ (posedge clk or posedge rst) begin
   K <= 0;
   
	case (KSState)	
	  `KSS_KEYREAD:	begin // KSS_KEYREAD state: Read key from input
	     if (rst) KSState <= `RST_STATE;
	     else begin
		      KSState <= `KSS_KEYSCHED1;
		key <= password_input;
		temp_K <= password_input;
		
	     end 
	  end
	  /*
for i from 0 to 255
    S[i] := i
endfor
*/
	  `KSS_KEYSCHED1:	begin // KSS_KEYSCHED1: Increment counter for S initialization
	     if(rst) KSState <= `RST_STATE;
	     else begin
		S[i] <= i;
		if (i == 8'hFF)
		  begin
		     KSState <= `KSS_KEYSCHED2;
		     i <= 8'h00;
		  end
		else	i <= i +1;
	     end
	  end // case: `KSS_KEYSCHED1
	  
/*		
j := 0
for i from 0 to 255
    j := (j + S[i] + key[i mod keylength]) mod 256
    swap values of S[i] and S[j]
endfor
*/
	  `KSS_KEYSCHED2:	begin // KSS_KEYSCHED2: Initialize S array
	     if(rst) KSState <= `RST_STATE;
	     else begin
		j <= (j + S[i] + key[i % `KEY_SIZE]);
		KSState <= `KSS_KEYSCHED3;
	     end
	  end
	  
	  `KSS_KEYSCHED3:	begin // KSS_KEYSCHED3: S array permutation
	     if(rst) KSState <= `RST_STATE;
	     else begin
		S[i]<=S[j];
		S[j]<=S[i];
		if (i == 8'hFF)
		  begin
		     //KSState <= `KSS_CRYPTO;
		     KSState <= `RDY_STATE;
		     
		     i <= 8'h01;
		     j <= S[1];
		     discardCount <= 10'h0;
		     output_ready <= 0; // K not valid yet
		     
		  end
		else	begin
		   i <= i + 1;
		   KSState <= `KSS_KEYSCHED2;
		end
	     end // else: !if(rst)
	  end
/*				
i := 0
j := 0
while GeneratingOutput:
    i := (i + 1) mod 256
    j := (j + S[i]) mod 256
    swap values of S[i] and S[j]
    K := S[(S[i] + S[j]) mod 256]
    output K
endwhile
*/
	  `RDY_STATE : begin
	     		     
	     i <= 8'h01;
	     j <= S[1];
	     
	     if(valid) KSState <= `KSS_CRYPTO;
	  end
	  
	  
	  `KSS_CRYPTO: begin
	     if(rst) KSState <= `RST_STATE;
	     else if(!valid) KSState <= `RDY_STATE;

	     else begin
		S[i] <= S[j];
		S[j] <= S[i]; // We can do this because of verilog.
		tmp<=S[i]+S[j];
		KSState <= `KSS_CRYPTO2;
		output_ready <= 0; 
	     end
	  end
	  
	  `KSS_CRYPTO2: begin
	     if(rst) KSState <= `RST_STATE;
	     else if(!valid) KSState <= `RDY_STATE;

	     else begin
		K <= S[tmp];//S[ S[i]+S[j] ];

		output_ready <= 1; // Valid K at output
		i <= i+1;
		// Here is the secret of 1-clock: we develop all possible values of j in the future
		if (j==i+1) 
   		  j <= (j + S[i]);
		else
		  if (i==255) j <= (j + S[0]);
		  else j <= (j + S[i+1]);
	//	$display ("rc4: output = %08X",K);		
		KSState <= `KSS_CRYPTO;
	     end // else: !if(rst)
	    // K <= temp_K;
	     
	  end // case: `KSS_CRYPTO2
	  
	  `RST_STATE: begin
	     i <= 8'h0;
	     KSState <= `KSS_KEYREAD;
	     output_ready <= 0;
	     j <= 0; 
	  end

	  
	  
	  default:	KSState <= `RST_STATE;
	  
	endcase
end 

   assign init_done = (KSState == `KSS_CRYPTO || KSState == `KSS_CRYPTO2 || KSState == `RDY_STATE);
   
endmodule

rc4/decrypt.v

module decrypt(clk, rst, password, data_in, data_out, init_done,  valid, out_valid);
   input wire clk, rst;
   input wire [7:0] password, data_in;
   output reg [7:0] data_out;
   wire 	    output_ready;
   reg [7:0] 	    temp_K = 0;
   reg [7:0] 	    temp_K2 = 0;
   
   reg [7:0] 	    prev_K;
   reg [7:0] 	    data_in_temp;
   input 	    valid;
   
   
   output wire 	    init_done;
   wire [7:0] 	    K;
   input wire 	    done;   
   reg [2:0] 	    state;
   output reg 	    out_valid = 0;
   reg 		    temp_out_valid = 0;
   
   reg 		    temp_out_valid2;
   
   rc4 device(.clk(clk), .rst(rst), .output_ready(output_ready),.password_input(password),.K(K), .init_done(init_done), .valid(valid));
   always @ (posedge clk) begin
      data_out <= 0;
      out_valid <= 0;
      temp_K2 <= password;
      temp_out_valid2 <= 0;
      temp_out_valid <= 0;
      
      if(valid) begin	 
	 data_out <= temp_K2 ^ data_in;
	 temp_out_valid <= 1;
	 temp_out_valid2 <= temp_out_valid;
	 
	 out_valid <= temp_out_valid2;
      end
   end // always @ (posedge clk)
   always @ (posedge output_ready) begin
	 temp_K <= K;
      
	 
   end

   
endmodule // decrypt

rc4/encrypt.v
module encrypt(clk, rst, password, data_in, data_out, init_done, valid, out_valid);
   input wire clk, rst;
   input wire [7:0] password, data_in;
   output reg [7:0] data_out;
   wire 	    output_ready;
   wire [7:0] 	    K;
   reg [7:0] 	    prev_K;
   output wire 	    init_done;

   reg [2:0] 	    state;
   reg [7:0] 	    temp_K = 0;
   reg [7:0] 	    temp_K2 = 0;

   input 	    valid;
   output  reg	    out_valid = 0;
   
   
   
   rc4 device(.clk(clk), .rst(rst), .output_ready(output_ready),.password_input(password),.K(K), .init_done(init_done), .valid(valid));
   always @ (posedge clk) begin
      data_out <= 0;
      out_valid <= 0;
      temp_K <= password;
      
      if(valid) begin
	 data_out <= temp_K ^ data_in;
	 out_valid <= 1;
	 
      end
   end // always @ (posedge clk)
   always @ (posedge output_ready) begin
	 temp_K2 <= K;
	 
   end
   
   
endmodule // decrypt

rc4/rc4_top.v
`define START 0
`define PROGRESS 1
`define VALID 2

module rc4_top(clk, rst, password, data_in, data_out, valid1, valid);
   input wire clk, rst;
   input wire [7:0] password, data_in;
   output wire [7:0] data_out;
   input 	     valid1, valid;
   
   wire 	     rdy_en, rdy_de, done_en, done_de;
   wire [7:0] 	     data_out_temp ;
   reg [7:0] 	     data_out_temp2 = 0;
   reg [7:0] 	     data_out_temp3 = 0;

   wire 	     init_done1, init_done2;
   reg [7:0] 	     storage[255:0];
   wire 	     start_en, start_de;
   
   reg [31:0] 	     i = 0;
   reg [31:0] 	     j = 0;
   
   reg [1:0] 	     state1 = 0;
   reg [1:0] 	     state2 = 0;
   reg 	     valid2;
   
   wire      outvalid1, outvalid2;
   
   
   encrypt encrypt_d(.clk(clk), .rst(rst), .password(password), .data_in(data_in) ,.data_out(data_out_temp), .init_done(init_done1), .valid(valid1), .out_valid(out_valid1));
   decrypt decrypt_d(.clk(clk), .rst(rst), .password(password), .data_in(data_out_temp2) ,.data_out(data_out), .init_done(init_done2), .valid(valid2), .out_valid(outvalid2));
   

   always @(posedge clk) begin

      if(valid1) begin
	 storage[i] <= data_out_temp;
	 i <= i + 1;
      end
      else i <= 0;
      
   end // always @ (posedge clk)
   

   always @(posedge clk) begin
      valid2 <= 0;
      data_out_temp2 <= 0;
      data_out_temp3 <= storage[j];
      
      if(valid) begin
	 valid2 <= 1;
	 data_out_temp2 <= data_out_temp3;
	 j <= j + 1;
	 
      end
      else
	j <= 0;
      

   end // always @ (posedge clk)

endmodule // rc4_top

rc4/rc4_top_tb.v

module rc4_top_tb();
   reg clk, rst;
   reg [7:0] password, data_in;
   wire [7:0] data_out;
   reg 	      valid1;
   reg 	      rdy_de, rdy_en, done_en, done_de;
   
   reg 	      valid;
   task delay(input [31:0] num);
      integer i;
      
      for (i=0; i<num; i=i+1)
	@(posedge clk) ;
   endtask// delay
   
   
   rc4_top DUT(clk, rst, password, data_in, data_out, valid1, valid);
   initial begin
      $display("hello, world");
      $dumpfile("t.vcd");
      $dumpvars;

      #100000;
      $finish;
   end
   initial begin
      clk = 0;
      forever begin
	 #5;
	 clk = ~clk;
      end
   end

   initial begin
      rst <= 1;
      data_in <= 0;
      password <= 0;
      rdy_en <= 0;
      rdy_de <= 0;
      done_en <= 0;
      done_de <= 0;
      valid <= 0;
      valid1 <= 0;
      
      delay(2);
      rst <= 0;
      password <= 137;
      delay(1000);
      

      

      delay(2);
      valid1 <= 1;
      
      data_in <= 5;
      delay(2);
      
      data_in <= 10;
      delay(2);
      data_in <= 20;
      delay(2);
      data_in <= 30;
      delay(2);
      data_in <= 40;
      delay(2);
      valid1 <= 0;
      
 
      valid <= 1;
      
      delay(10);
  
      

      
      delay(120);
      
  
      
      valid <= 0;
      
      delay(10);

      
      delay(2);
      done_de <= 0;
      done_en <= 0;




      
      delay(100);
   
      delay(10);
      
      valid1 <= 1;
      
      data_in <= 5;
      delay(2);
      
      data_in <= 10;
      delay(2);
      data_in <= 20;
      delay(2);
      data_in <= 30;
      delay(2);
      data_in <= 40;
      delay(4);
      valid1 <= 0;
      
      delay(10);
      valid <= 1;
      
      

      
      delay(130);
      

      valid <= 0;
      
      delay(10);
      

      
         
      
   end
endmodule // rc4_top_tb

rc4/t.vcd
$date
	Mon Jun  7 22:42:40 2021
$end
$version
	Icarus Verilog
$end
$timescale
	1s
$end
$scope module rc4_top_tb $end
$var wire 8 ! data_out [7:0] $end
$var reg 1 " clk $end
$var reg 8 # data_in [7:0] $end
$var reg 1 $ done_de $end
$var reg 1 % done_en $end
$var reg 8 & password [7:0] $end
$var reg 1 ' rdy_de $end
$var reg 1 ( rdy_en $end
$var reg 1 ) rst $end
$var reg 1 * valid $end
$var reg 1 + valid1 $end
$scope module DUT $end
$var wire 1 " clk $end
$var wire 8 , data_in [7:0] $end
$var wire 8 - password [7:0] $end
$var wire 1 ) rst $end
$var wire 1 * valid $end
$var wire 1 + valid1 $end
$var wire 1 . outvalid2 $end
$var wire 1 / out_valid1 $end
$var wire 1 0 init_done2 $end
$var wire 1 1 init_done1 $end
$var wire 8 2 data_out_temp [7:0] $end
$var wire 8 3 data_out [7:0] $end
$var reg 8 4 data_out_temp2 [7:0] $end
$var reg 8 5 data_out_temp3 [7:0] $end
$var reg 32 6 i [31:0] $end
$var reg 32 7 j [31:0] $end
$var reg 2 8 state1 [1:0] $end
$var reg 2 9 state2 [1:0] $end
$var reg 1 : valid2 $end
$scope module decrypt_d $end
$var wire 1 " clk $end
$var wire 8 ; data_in [7:0] $end
$var wire 1 < done $end
$var wire 8 = password [7:0] $end
$var wire 1 ) rst $end
$var wire 1 : valid $end
$var wire 1 > output_ready $end
$var wire 1 0 init_done $end
$var wire 8 ? K [7:0] $end
$var reg 8 @ data_out [7:0] $end
$var reg 1 . out_valid $end
$var reg 8 A temp_K [7:0] $end
$var reg 8 B temp_K2 [7:0] $end
$var reg 1 C temp_out_valid $end
$var reg 1 D temp_out_valid2 $end
$scope module device $end
$var wire 1 " clk $end
$var wire 1 0 init_done $end
$var wire 8 E password_input [7:0] $end
$var wire 1 ) rst $end
$var wire 1 F start $end
$var wire 1 : valid $end
$var reg 8 G K [7:0] $end
$var reg 4 H KSState [3:0] $end
$var reg 10 I discardCount [9:0] $end
$var reg 8 J i [7:0] $end
$var reg 8 K j [7:0] $end
$var reg 8 L key [7:0] $end
$var reg 1 > output_ready $end
$var reg 8 M temp_K [7:0] $end
$var reg 8 N tmp [7:0] $end
$upscope $end
$upscope $end
$scope module encrypt_d $end
$var wire 1 " clk $end
$var wire 8 O data_in [7:0] $end
$var wire 8 P password [7:0] $end
$var wire 1 ) rst $end
$var wire 1 + valid $end
$var wire 1 Q output_ready $end
$var wire 1 1 init_done $end
$var wire 8 R K [7:0] $end
$var reg 8 S data_out [7:0] $end
$var reg 1 / out_valid $end
$var reg 8 T temp_K [7:0] $end
$var reg 8 U temp_K2 [7:0] $end
$scope module device $end
$var wire 1 " clk $end
$var wire 1 1 init_done $end
$var wire 8 V password_input [7:0] $end
$var wire 1 ) rst $end
$var wire 1 W start $end
$var wire 1 + valid $end
$var reg 8 X K [7:0] $end
$var reg 4 Y KSState [3:0] $end
$var reg 10 Z discardCount [9:0] $end
$var reg 8 [ i [7:0] $end
$var reg 8 \ j [7:0] $end
$var reg 8 ] key [7:0] $end
$var reg 1 Q output_ready $end
$var reg 8 ^ temp_K [7:0] $end
$var reg 8 _ tmp [7:0] $end
$upscope $end
$upscope $end
$upscope $end
$scope task delay $end
$var reg 32 ` num [31:0] $end
$var integer 32 a i [31:0] $end
$upscope $end
$upscope $end
$enddefinitions $end
#0
$dumpvars
b0 a
b10 `
bx _
bx ^
bx ]
bx \
bx [
bx Z
b110 Y
b0 X
zW
b0 V
b0 U
b0 T
bx S
b0 R
xQ
b0 P
b0 O
bx N
bx M
bx L
bx K
bx J
bx I
b110 H
b0 G
zF
b0 E
xD
0C
b0 B
b0 A
bx @
b0 ?
x>
b0 =
z<
b0 ;
x:
b0 9
b0 8
b0 7
b0 6
b0 5
b0 4
bx 3
bx 2
01
00
0/
0.
b0 -
b0 ,
0+
0*
1)
0(
0'
b0 &
0%
0$
b0 #
0"
bx !
$end
#5
b0 K
0>
b0 H
b0 J
b0 \
0Q
b0 Y
b0 [
b0 2
b0 S
0D
b0 !
b0 3
b0 @
bx 5
0:
b1 a
1"
#10
0"
#15
b110 Y
b110 H
b10001001 &
b10001001 -
b10001001 =
b10001001 E
b10001001 P
b10001001 V
0)
b1111101000 `
b0 a
1"
#20
0"
#25
b0 H
b0 Y
b10001001 T
b10001001 B
b1 a
1"
#30
0"
#35
b10001001 ^
b10001001 ]
b1 Y
b10001001 M
b10001001 L
b1 H
b10 a
1"
#40
0"
#45
b1 J
b1 [
b11 a
1"
#50
0"
#55
b10 [
b10 J
b100 a
1"
#60
0"
#65
b11 J
b11 [
b101 a
1"
#70
0"
#75
b100 [
b100 J
b110 a
1"
#80
0"
#85
b101 J
b101 [
b111 a
1"
#90
0"
#95
b110 [
b110 J
b1000 a
1"
#100
0"
#105
b111 J
b111 [
b1001 a
1"
#110
0"
#115
b1000 [
b1000 J
b1010 a
1"
#120
0"
#125
b1001 J
b1001 [
b1011 a
1"
#130
0"
#135
b1010 [
b1010 J
b1100 a
1"
#140
0"
#145
b1011 J
b1011 [
b1101 a
1"
#150
0"
#155
b1100 [
b1100 J
b1110 a
1"
#160
0"
#165
b1101 J
b1101 [
b1111 a
1"
#170
0"
#175
b1110 [
b1110 J
b10000 a
1"
#180
0"
#185
b1111 J
b1111 [
b10001 a
1"
#190
0"
#195
b10000 [
b10000 J
b10010 a
1"
#200
0"
#205
b10001 J
b10001 [
b10011 a
1"
#210
0"
#215
b10010 [
b10010 J
b10100 a
1"
#220
0"
#225
b10011 J
b10011 [
b10101 a
1"
#230
0"
#235
b10100 [
b10100 J
b10110 a
1"
#240
0"
#245
b10101 J
b10101 [
b10111 a
1"
#250
0"
#255
b10110 [
b10110 J
b11000 a
1"
#260
0"
#265
b10111 J
b10111 [
b11001 a
1"
#270
0"
#275
b11000 [
b11000 J
b11010 a
1"
#280
0"
#285
b11001 J
b11001 [
b11011 a
1"
#290
0"
#295
b11010 [
b11010 J
b11100 a
1"
#300
0"
#305
b11011 J
b11011 [
b11101 a
1"
#310
0"
#315
b11100 [
b11100 J
b11110 a
1"
#320
0"
#325
b11101 J
b11101 [
b11111 a
1"
#330
0"
#335
b11110 [
b11110 J
b100000 a
1"
#340
0"
#345
b11111 J
b11111 [
b100001 a
1"
#350
0"
#355
b100000 [
b100000 J
b100010 a
1"
#360
0"
#365
b100001 J
b100001 [
b100011 a
1"
#370
0"
#375
b100010 [
b100010 J
b100100 a
1"
#380
0"
#385
b100011 J
b100011 [
b100101 a
1"
#390
0"
#395
b100100 [
b100100 J
b100110 a
1"
#400
0"
#405
b100101 J
b100101 [
b100111 a
1"
#410
0"
#415
b100110 [
b100110 J
b101000 a
1"
#420
0"
#425
b100111 J
b100111 [
b101001 a
1"
#430
0"
#435
b101000 [
b101000 J
b101010 a
1"
#440
0"
#445
b101001 J
b101001 [
b101011 a
1"
#450
0"
#455
b101010 [
b101010 J
b101100 a
1"
#460
0"
#465
b101011 J
b101011 [
b101101 a
1"
#470
0"
#475
b101100 [
b101100 J
b101110 a
1"
#480
0"
#485
b101101 J
b101101 [
b101111 a
1"
#490
0"
#495
b101110 [
b101110 J
b110000 a
1"
#500
0"
#505
b101111 J
b101111 [
b110001 a
1"
#510
0"
#515
b110000 [
b110000 J
b110010 a
1"
#520
0"
#525
b110001 J
b110001 [
b110011 a
1"
#530
0"
#535
b110010 [
b110010 J
b110100 a
1"
#540
0"
#545
b110011 J
b110011 [
b110101 a
1"
#550
0"
#555
b110100 [
b110100 J
b110110 a
1"
#560
0"
#565
b110101 J
b110101 [
b110111 a
1"
#570
0"
#575
b110110 [
b110110 J
b111000 a
1"
#580
0"
#585
b110111 J
b110111 [
b111001 a
1"
#590
0"
#595
b111000 [
b111000 J
b111010 a
1"
#600
0"
#605
b111001 J
b111001 [
b111011 a
1"
#610
0"
#615
b111010 [
b111010 J
b111100 a
1"
#620
0"
#625
b111011 J
b111011 [
b111101 a
1"
#630
0"
#635
b111100 [
b111100 J
b111110 a
1"
#640
0"
#645
b111101 J
b111101 [
b111111 a
1"
#650
0"
#655
b111110 [
b111110 J
b1000000 a
1"
#660
0"
#665
b111111 J
b111111 [
b1000001 a
1"
#670
0"
#675
b1000000 [
b1000000 J
b1000010 a
1"
#680
0"
#685
b1000001 J
b1000001 [
b1000011 a
1"
#690
0"
#695
b1000010 [
b1000010 J
b1000100 a
1"
#700
0"
#705
b1000011 J
b1000011 [
b1000101 a
1"
#710
0"
#715
b1000100 [
b1000100 J
b1000110 a
1"
#720
0"
#725
b1000101 J
b1000101 [
b1000111 a
1"
#730
0"
#735
b1000110 [
b1000110 J
b1001000 a
1"
#740
0"
#745
b1000111 J
b1000111 [
b1001001 a
1"
#750
0"
#755
b1001000 [
b1001000 J
b1001010 a
1"
#760
0"
#765
b1001001 J
b1001001 [
b1001011 a
1"
#770
0"
#775
b1001010 [
b1001010 J
b1001100 a
1"
#780
0"
#785
b1001011 J
b1001011 [
b1001101 a
1"
#790
0"
#795
b1001100 [
b1001100 J
b1001110 a
1"
#800
0"
#805
b1001101 J
b1001101 [
b1001111 a
1"
#810
0"
#815
b1001110 [
b1001110 J
b1010000 a
1"
#820
0"
#825
b1001111 J
b1001111 [
b1010001 a
1"
#830
0"
#835
b1010000 [
b1010000 J
b1010010 a
1"
#840
0"
#845
b1010001 J
b1010001 [
b1010011 a
1"
#850
0"
#855
b1010010 [
b1010010 J
b1010100 a
1"
#860
0"
#865
b1010011 J
b1010011 [
b1010101 a
1"
#870
0"
#875
b1010100 [
b1010100 J
b1010110 a
1"
#880
0"
#885
b1010101 J
b1010101 [
b1010111 a
1"
#890
0"
#895
b1010110 [
b1010110 J
b1011000 a
1"
#900
0"
#905
b1010111 J
b1010111 [
b1011001 a
1"
#910
0"
#915
b1011000 [
b1011000 J
b1011010 a
1"
#920
0"
#925
b1011001 J
b1011001 [
b1011011 a
1"
#930
0"
#935
b1011010 [
b1011010 J
b1011100 a
1"
#940
0"
#945
b1011011 J
b1011011 [
b1011101 a
1"
#950
0"
#955
b1011100 [
b1011100 J
b1011110 a
1"
#960
0"
#965
b1011101 J
b1011101 [
b1011111 a
1"
#970
0"
#975
b1011110 [
b1011110 J
b1100000 a
1"
#980
0"
#985
b1011111 J
b1011111 [
b1100001 a
1"
#990
0"
#995
b1100000 [
b1100000 J
b1100010 a
1"
#1000
0"
#1005
b1100001 J
b1100001 [
b1100011 a
1"
#1010
0"
#1015
b1100010 [
b1100010 J
b1100100 a
1"
#1020
0"
#1025
b1100011 J
b1100011 [
b1100101 a
1"
#1030
0"
#1035
b1100100 [
b1100100 J
b1100110 a
1"
#1040
0"
#1045
b1100101 J
b1100101 [
b1100111 a
1"
#1050
0"
#1055
b1100110 [
b1100110 J
b1101000 a
1"
#1060
0"
#1065
b1100111 J
b1100111 [
b1101001 a
1"
#1070
0"
#1075
b1101000 [
b1101000 J
b1101010 a
1"
#1080
0"
#1085
b1101001 J
b1101001 [
b1101011 a
1"
#1090
0"
#1095
b1101010 [
b1101010 J
b1101100 a
1"
#1100
0"
#1105
b1101011 J
b1101011 [
b1101101 a
1"
#1110
0"
#1115
b1101100 [
b1101100 J
b1101110 a
1"
#1120
0"
#1125
b1101101 J
b1101101 [
b1101111 a
1"
#1130
0"
#1135
b1101110 [
b1101110 J
b1110000 a
1"
#1140
0"
#1145
b1101111 J
b1101111 [
b1110001 a
1"
#1150
0"
#1155
b1110000 [
b1110000 J
b1110010 a
1"
#1160
0"
#1165
b1110001 J
b1110001 [
b1110011 a
1"
#1170
0"
#1175
b1110010 [
b1110010 J
b1110100 a
1"
#1180
0"
#1185
b1110011 J
b1110011 [
b1110101 a
1"
#1190
0"
#1195
b1110100 [
b1110100 J
b1110110 a
1"
#1200
0"
#1205
b1110101 J
b1110101 [
b1110111 a
1"
#1210
0"
#1215
b1110110 [
b1110110 J
b1111000 a
1"
#1220
0"
#1225
b1110111 J
b1110111 [
b1111001 a
1"
#1230
0"
#1235
b1111000 [
b1111000 J
b1111010 a
1"
#1240
0"
#1245
b1111001 J
b1111001 [
b1111011 a
1"
#1250
0"
#1255
b1111010 [
b1111010 J
b1111100 a
1"
#1260
0"
#1265
b1111011 J
b1111011 [
b1111101 a
1"
#1270
0"
#1275
b1111100 [
b1111100 J
b1111110 a
1"
#1280
0"
#1285
b1111101 J
b1111101 [
b1111111 a
1"
#1290
0"
#1295
b1111110 [
b1111110 J
b10000000 a
1"
#1300
0"
#1305
b1111111 J
b1111111 [
b10000001 a
1"
#1310
0"
#1315
b10000000 [
b10000000 J
b10000010 a
1"
#1320
0"
#1325
b10000001 J
b10000001 [
b10000011 a
1"
#1330
0"
#1335
b10000010 [
b10000010 J
b10000100 a
1"
#1340
0"
#1345
b10000011 J
b10000011 [
b10000101 a
1"
#1350
0"
#1355
b10000100 [
b10000100 J
b10000110 a
1"
#1360
0"
#1365
b10000101 J
b10000101 [
b10000111 a
1"
#1370
0"
#1375
b10000110 [
b10000110 J
b10001000 a
1"
#1380
0"
#1385
b10000111 J
b10000111 [
b10001001 a
1"
#1390
0"
#1395
b10001000 [
b10001000 J
b10001010 a
1"
#1400
0"
#1405
b10001001 J
b10001001 [
b10001011 a
1"
#1410
0"
#1415
b10001010 [
b10001010 J
b10001100 a
1"
#1420
0"
#1425
b10001011 J
b10001011 [
b10001101 a
1"
#1430
0"
#1435
b10001100 [
b10001100 J
b10001110 a
1"
#1440
0"
#1445
b10001101 J
b10001101 [
b10001111 a
1"
#1450
0"
#1455
b10001110 [
b10001110 J
b10010000 a
1"
#1460
0"
#1465
b10001111 J
b10001111 [
b10010001 a
1"
#1470
0"
#1475
b10010000 [
b10010000 J
b10010010 a
1"
#1480
0"
#1485
b10010001 J
b10010001 [
b10010011 a
1"
#1490
0"
#1495
b10010010 [
b10010010 J
b10010100 a
1"
#1500
0"
#1505
b10010011 J
b10010011 [
b10010101 a
1"
#1510
0"
#1515
b10010100 [
b10010100 J
b10010110 a
1"
#1520
0"
#1525
b10010101 J
b10010101 [
b10010111 a
1"
#1530
0"
#1535
b10010110 [
b10010110 J
b10011000 a
1"
#1540
0"
#1545
b10010111 J
b10010111 [
b10011001 a
1"
#1550
0"
#1555
b10011000 [
b10011000 J
b10011010 a
1"
#1560
0"
#1565
b10011001 J
b10011001 [
b10011011 a
1"
#1570
0"
#1575
b10011010 [
b10011010 J
b10011100 a
1"
#1580
0"
#1585
b10011011 J
b10011011 [
b10011101 a
1"
#1590
0"
#1595
b10011100 [
b10011100 J
b10011110 a
1"
#1600
0"
#1605
b10011101 J
b10011101 [
b10011111 a
1"
#1610
0"
#1615
b10011110 [
b10011110 J
b10100000 a
1"
#1620
0"
#1625
b10011111 J
b10011111 [
b10100001 a
1"
#1630
0"
#1635
b10100000 [
b10100000 J
b10100010 a
1"
#1640
0"
#1645
b10100001 J
b10100001 [
b10100011 a
1"
#1650
0"
#1655
b10100010 [
b10100010 J
b10100100 a
1"
#1660
0"
#1665
b10100011 J
b10100011 [
b10100101 a
1"
#1670
0"
#1675
b10100100 [
b10100100 J
b10100110 a
1"
#1680
0"
#1685
b10100101 J
b10100101 [
b10100111 a
1"
#1690
0"
#1695
b10100110 [
b10100110 J
b10101000 a
1"
#1700
0"
#1705
b10100111 J
b10100111 [
b10101001 a
1"
#1710
0"
#1715
b10101000 [
b10101000 J
b10101010 a
1"
#1720
0"
#1725
b10101001 J
b10101001 [
b10101011 a
1"
#1730
0"
#1735
b10101010 [
b10101010 J
b10101100 a
1"
#1740
0"
#1745
b10101011 J
b10101011 [
b10101101 a
1"
#1750
0"
#1755
b10101100 [
b10101100 J
b10101110 a
1"
#1760
0"
#1765
b10101101 J
b10101101 [
b10101111 a
1"
#1770
0"
#1775
b10101110 [
b10101110 J
b10110000 a
1"
#1780
0"
#1785
b10101111 J
b10101111 [
b10110001 a
1"
#1790
0"
#1795
b10110000 [
b10110000 J
b10110010 a
1"
#1800
0"
#1805
b10110001 J
b10110001 [
b10110011 a
1"
#1810
0"
#1815
b10110010 [
b10110010 J
b10110100 a
1"
#1820
0"
#1825
b10110011 J
b10110011 [
b10110101 a
1"
#1830
0"
#1835
b10110100 [
b10110100 J
b10110110 a
1"
#1840
0"
#1845
b10110101 J
b10110101 [
b10110111 a
1"
#1850
0"
#1855
b10110110 [
b10110110 J
b10111000 a
1"
#1860
0"
#1865
b10110111 J
b10110111 [
b10111001 a
1"
#1870
0"
#1875
b10111000 [
b10111000 J
b10111010 a
1"
#1880
0"
#1885
b10111001 J
b10111001 [
b10111011 a
1"
#1890
0"
#1895
b10111010 [
b10111010 J
b10111100 a
1"
#1900
0"
#1905
b10111011 J
b10111011 [
b10111101 a
1"
#1910
0"
#1915
b10111100 [
b10111100 J
b10111110 a
1"
#1920
0"
#1925
b10111101 J
b10111101 [
b10111111 a
1"
#1930
0"
#1935
b10111110 [
b10111110 J
b11000000 a
1"
#1940
0"
#1945
b10111111 J
b10111111 [
b11000001 a
1"
#1950
0"
#1955
b11000000 [
b11000000 J
b11000010 a
1"
#1960
0"
#1965
b11000001 J
b11000001 [
b11000011 a
1"
#1970
0"
#1975
b11000010 [
b11000010 J
b11000100 a
1"
#1980
0"
#1985
b11000011 J
b11000011 [
b11000101 a
1"
#1990
0"
#1995
b11000100 [
b11000100 J
b11000110 a
1"
#2000
0"
#2005
b11000101 J
b11000101 [
b11000111 a
1"
#2010
0"
#2015
b11000110 [
b11000110 J
b11001000 a
1"
#2020
0"
#2025
b11000111 J
b11000111 [
b11001001 a
1"
#2030
0"
#2035
b11001000 [
b11001000 J
b11001010 a
1"
#2040
0"
#2045
b11001001 J
b11001001 [
b11001011 a
1"
#2050
0"
#2055
b11001010 [
b11001010 J
b11001100 a
1"
#2060
0"
#2065
b11001011 J
b11001011 [
b11001101 a
1"
#2070
0"
#2075
b11001100 [
b11001100 J
b11001110 a
1"
#2080
0"
#2085
b11001101 J
b11001101 [
b11001111 a
1"
#2090
0"
#2095
b11001110 [
b11001110 J
b11010000 a
1"
#2100
0"
#2105
b11001111 J
b11001111 [
b11010001 a
1"
#2110
0"
#2115
b11010000 [
b11010000 J
b11010010 a
1"
#2120
0"
#2125
b11010001 J
b11010001 [
b11010011 a
1"
#2130
0"
#2135
b11010010 [
b11010010 J
b11010100 a
1"
#2140
0"
#2145
b11010011 J
b11010011 [
b11010101 a
1"
#2150
0"
#2155
b11010100 [
b11010100 J
b11010110 a
1"
#2160
0"
#2165
b11010101 J
b11010101 [
b11010111 a
1"
#2170
0"
#2175
b11010110 [
b11010110 J
b11011000 a
1"
#2180
0"
#2185
b11010111 J
b11010111 [
b11011001 a
1"
#2190
0"
#2195
b11011000 [
b11011000 J
b11011010 a
1"
#2200
0"
#2205
b11011001 J
b11011001 [
b11011011 a
1"
#2210
0"
#2215
b11011010 [
b11011010 J
b11011100 a
1"
#2220
0"
#2225
b11011011 J
b11011011 [
b11011101 a
1"
#2230
0"
#2235
b11011100 [
b11011100 J
b11011110 a
1"
#2240
0"
#2245
b11011101 J
b11011101 [
b11011111 a
1"
#2250
0"
#2255
b11011110 [
b11011110 J
b11100000 a
1"
#2260
0"
#2265
b11011111 J
b11011111 [
b11100001 a
1"
#2270
0"
#2275
b11100000 [
b11100000 J
b11100010 a
1"
#2280
0"
#2285
b11100001 J
b11100001 [
b11100011 a
1"
#2290
0"
#2295
b11100010 [
b11100010 J
b11100100 a
1"
#2300
0"
#2305
b11100011 J
b11100011 [
b11100101 a
1"
#2310
0"
#2315
b11100100 [
b11100100 J
b11100110 a
1"
#2320
0"
#2325
b11100101 J
b11100101 [
b11100111 a
1"
#2330
0"
#2335
b11100110 [
b11100110 J
b11101000 a
1"
#2340
0"
#2345
b11100111 J
b11100111 [
b11101001 a
1"
#2350
0"
#2355
b11101000 [
b11101000 J
b11101010 a
1"
#2360
0"
#2365
b11101001 J
b11101001 [
b11101011 a
1"
#2370
0"
#2375
b11101010 [
b11101010 J
b11101100 a
1"
#2380
0"
#2385
b11101011 J
b11101011 [
b11101101 a
1"
#2390
0"
#2395
b11101100 [
b11101100 J
b11101110 a
1"
#2400
0"
#2405
b11101101 J
b11101101 [
b11101111 a
1"
