rc4/rc4.v
`define KEY_SIZE 7
module rc4(clk,rst,output_ready,password_input,K, init_done, valid);

input clk; // Clock
input rst; // Reset
input [7:0] password_input; // Password input
output output_ready; // Output valid
output [7:0] K; // Output port
   input     valid;
   

wire clk, rst; // clock, reset
reg output_ready;
wire [7:0] password_input;
output wire    init_done;
input wire  start;
   
   

/* RC4 PRGA */

// Key
reg [7:0] key;
// S array
reg [7:0] S[0:256];
reg [9:0] discardCount;

// Key-scheduling state
`define KSS_KEYREAD 4'h0
`define KSS_KEYSCHED1 4'h1
`define KSS_KEYSCHED2 4'h2
`define KSS_KEYSCHED3 4'h3
`define KSS_CRYPTO 	 4'h4
`define KSS_CRYPTO2 	 4'h5
`define RST_STATE 4'h6
`define RDY_STATE 4'h7
`define DONE_STATE 4'h8
   
// Variable names from http://en.wikipedia.org/wiki/RC4
   reg [3:0] KSState;
reg [7:0] i; // Counter
reg [7:0] j;
reg [7:0] K;
   reg [7:0] temp_K;
   
reg [7:0] tmp;

always @ (posedge clk or posedge rst) begin
   K <= 0;
   
	case (KSState)	
	  `KSS_KEYREAD:	begin // KSS_KEYREAD state: Read key from input
	     if (rst) KSState <= `RST_STATE;
	     else begin
		      KSState <= `KSS_KEYSCHED1;
		key <= password_input;
		temp_K <= password_input;
		
	     end 
	  end
	  /*
for i from 0 to 255
    S[i] := i
endfor
*/
	  `KSS_KEYSCHED1:	begin // KSS_KEYSCHED1: Increment counter for S initialization
	     if(rst) KSState <= `RST_STATE;
	     else begin
		S[i] <= i;
		if (i == 8'hFF)
		  begin
		     KSState <= `KSS_KEYSCHED2;
		     i <= 8'h00;
		  end
		else	i <= i +1;
	     end
	  end // case: `KSS_KEYSCHED1
	  
/*		
j := 0
for i from 0 to 255
    j := (j + S[i] + key[i mod keylength]) mod 256
    swap values of S[i] and S[j]
endfor
*/
	  `KSS_KEYSCHED2:	begin // KSS_KEYSCHED2: Initialize S array
	     if(rst) KSState <= `RST_STATE;
	     else begin
		j <= (j + S[i] + key[i % `KEY_SIZE]);
		KSState <= `KSS_KEYSCHED3;
	     end
	  end
	  
	  `KSS_KEYSCHED3:	begin // KSS_KEYSCHED3: S array permutation
	     if(rst) KSState <= `RST_STATE;
	     else begin
		S[i]<=S[j];
		S[j]<=S[i];
		if (i == 8'hFF)
		  begin
		     //KSState <= `KSS_CRYPTO;
		     KSState <= `RDY_STATE;
		     
		     i <= 8'h01;
		     j <= S[1];
		     discardCount <= 10'h0;
		     output_ready <= 0; // K not valid yet
		     
		  end
		else	begin
		   i <= i + 1;
		   KSState <= `KSS_KEYSCHED2;
		end
	     end // else: !if(rst)
	  end
/*				
i := 0
j := 0
while GeneratingOutput:
    i := (i + 1) mod 256
    j := (j + S[i]) mod 256
    swap values of S[i] and S[j]
    K := S[(S[i] + S[j]) mod 256]
    output K
endwhile
*/
	  `RDY_STATE : begin
	     		     
	     i <= 8'h01;
	     j <= S[1];
	     
	     if(valid) KSState <= `KSS_CRYPTO;
	  end
	  
	  
	  `KSS_CRYPTO: begin
	     if(rst) KSState <= `RST_STATE;
	     
	     else begin
		S[i] <= S[j];
		S[j] <= S[i]; // We can do this because of verilog.
		tmp<=S[i]+S[j];
		KSState <= `KSS_CRYPTO2;
		output_ready <= 0; 
	     end
	  end
	  
	  `KSS_CRYPTO2: begin
	     if(rst) KSState <= `RST_STATE;

	     else begin
		K <= S[tmp];//S[ S[i]+S[j] ];

		output_ready <= 1; // Valid K at output
		i <= i+1;
		// Here is the secret of 1-clock: we develop all possible values of j in the future
		if (j==i+1) 
   		  j <= (j + S[i]);
		else
		  if (i==255) j <= (j + S[0]);
		  else j <= (j + S[i+1]);
	//	$display ("rc4: output = %08X",K);		
		KSState <= `KSS_CRYPTO;
	     end // else: !if(rst)
	    // K <= temp_K;
	     
	  end // case: `KSS_CRYPTO2
	  
	  `RST_STATE: begin
	     i <= 8'h0;
	     KSState <= `KSS_KEYREAD;
	     output_ready <= 0;
	     j <= 0; 
	  end

	  
	  
	  default:	KSState <= `RST_STATE;
	  
	endcase
end 

   assign init_done = (KSState == `KSS_CRYPTO || KSState == `KSS_CRYPTO2 || KSState == `RDY_STATE);
   
endmodule

rc4/decrypt.v

module decrypt(clk, rst, password, data_in, data_out, init_done,  valid, out_valid);
   input wire clk, rst;
   input wire [7:0] password, data_in;
   output reg [7:0] data_out;
   wire 	    output_ready;
   reg [7:0] 	    temp_K = 0;
   reg [7:0] 	    temp_K2 = 0;
   
   reg [7:0] 	    prev_K;
   reg [7:0] 	    data_in_temp;
   input 	    valid;
   
   
   output wire 	    init_done;
   wire [7:0] 	    K;
   input wire 	    done;   
   reg [2:0] 	    state;
   output reg 	    out_valid = 0;
   reg 		    temp_out_valid = 0;
   
   
   rc4 device(.clk(clk), .rst(rst), .output_ready(output_ready),.password_input(password),.K(K), .init_done(init_done), .valid(valid));
   always @ (posedge clk) begin
      data_out <= 0;
      out_valid <= 0;
      temp_K <= password;
      
      if(valid) begin	 
	 data_out <= temp_K ^ data_in;
	 temp_out_valid <= 1;
	 out_valid <= temp_out_valid;
	 
	 
	 
      end
   end

endmodule // decrypt

rc4/encrypt.v


module encrypt(clk, rst, password, data_in, data_out, init_done, valid, out_valid);
   input wire clk, rst;
   input wire [7:0] password, data_in;
   output reg [7:0] data_out;
   wire 	    output_ready;
   wire [7:0] 	    K;
   reg [7:0] 	    prev_K;
   output wire 	    init_done;

   reg [2:0] 	    state;
   reg [7:0] 	    temp_K = 0;
   input 	    valid;
   output  reg	    out_valid = 0;
   
   
   
   rc4 device(.clk(clk), .rst(rst), .output_ready(output_ready),.password_input(password),.K(K), .init_done(init_done), .valid(valid));
   always @ (posedge clk) begin
      data_out <= 0;
      out_valid <= 0;
      temp_K <= password;
      
      if(valid) begin
	 data_out <= temp_K ^ data_in;
	 out_valid <= 1;
	 
      end
   end
   
endmodule // decrypt

Part3/rc4_top.v
`define START 0
`define PROGRESS 1
`define VALID 2

module rc4_top(clk, rst, password, data_in, data_out, valid1, valid);
   input wire clk, rst;
   input wire [7:0] password, data_in;
   output wire [7:0] data_out;
   input 	     valid1, valid;
   
   wire 	     rdy_en, rdy_de, done_en, done_de;
   wire [7:0] 	     data_out_temp ;
   reg [7:0] 	     data_out_temp2 = 0;
   wire 	     init_done1, init_done2;
   reg [7:0] 	     storage[255:0];
   wire 	     start_en, start_de;
   
   reg [31:0] 	     i = 0;
   reg [31:0] 	     j = 0;
   
   reg [1:0] 	     state1 = 0;
   reg [1:0] 	     state2 = 0;
   reg 	     valid2;
   
   wire      outvalid1, outvalid2;
   
   
   encrypt encrypt_d(.clk(clk), .rst(rst), .password(password), .data_in(data_in) ,.data_out(data_out_temp), .init_done(init_done1), .valid(valid1), .out_valid(out_valid1));
   decrypt decrypt_d(.clk(clk), .rst(rst), .password(password), .data_in(data_out_temp2) ,.data_out(data_out), .init_done(init_done2), .valid(valid2), .out_valid(outvalid2));
   

   always @(posedge clk) begin

      if(valid1) begin
	 storage[i] <= data_out_temp;
	 i <= i + 1;
      end
      else i <= 0;
      
   end // always @ (posedge clk)
   

   always @(posedge clk) begin
      valid2 <= 0;
      data_out_temp2 <= 0;
      
      if(valid) begin
	 valid2 <= 1;
	 data_out_temp2 <= storage[j];
	 j <= j + 1;
	 
      end
      else
	j <= 0;
      

   end // always @ (posedge clk)

endmodule // rc4_top

rc4/rc4_top_tb.v

module rc4_top_tb();
   reg clk, rst;
   reg [7:0] password, data_in;
   wire [7:0] data_out;
   reg 	      valid1;
   reg 	      rdy_de, rdy_en, done_en, done_de;
   
   reg 	      valid;
  
   
   rc4_top DUT(clk, rst, password, data_in, data_out, valid1, valid);
   initial begin
      $display("hello, world");
      $dumpfile("t.vcd");
      $dumpvars;

      #100000;
      $finish;
   end
   initial begin
      clk = 0;
      forever begin
	 #5;
	 clk = ~clk;
      end
   end

   initial begin
      rst <= 1;
      data_in <= 0;
      password <= 0;
      rdy_en <= 0;
      rdy_de <= 0;
      done_en <= 0;
      done_de <= 0;
      valid <= 0;
      valid1 <= 0;
      
      #10;
      rst <= 0;
      password <= 1;
      #8500;

      

      #10;
      valid1 <= 1;
      
      rdy_en <= 1;
      data_in <= 5;
      #10;
      
      data_in <= 10;
      #10;
      data_in <= 20;
      #10;
      data_in <= 30;
      #10;
      data_in <= 40;
      #40;
      rdy_en <= 0;
      valid1 <= 0;
      
      done_en <= 1;
      valid <= 1;
      
      #10;
  
      

      
      #150;
      #10;
      
      valid <= 0;
      
      #10;

      
      #20;
      done_de <= 0;
      done_en <= 0;




      
      #100;
   
      #10;
      
      valid1 <= 1;
      
      data_in <= 5;
      #20;
      
      data_in <= 10;
      #20;
      data_in <= 20;
      #20;
      data_in <= 30;
      #20;
      data_in <= 40;
      #40;
      valid1 <= 0;
      
      #10;
      valid <= 1;
      
      

      
      #150;
      #10;
      
      rdy_de <= 0;

      valid <= 0;
      
      #10;
      
      #20;
      done_de <= 0;
      done_en <= 0;
      
         
      
   end
endmodule // rc4_top_tb

rc4/t.vcd
$date
	Sun Jun  6 22:50:29 2021
$end
$version
	Icarus Verilog
$end
$timescale
	1s
$end
$scope module rc4_top_tb $end
$var wire 8 ! data_out [7:0] $end
$var reg 1 " clk $end
$var reg 8 # data_in [7:0] $end
$var reg 1 $ done_de $end
$var reg 1 % done_en $end
$var reg 8 & password [7:0] $end
$var reg 1 ' rdy_de $end
$var reg 1 ( rdy_en $end
$var reg 1 ) rst $end
$var reg 1 * valid $end
$var reg 1 + valid1 $end
$scope module DUT $end
$var wire 1 " clk $end
$var wire 8 , data_in [7:0] $end
$var wire 8 - password [7:0] $end
$var wire 1 ) rst $end
$var wire 1 * valid $end
$var wire 1 + valid1 $end
$var wire 1 . outvalid2 $end
$var wire 1 / out_valid1 $end
$var wire 1 0 init_done2 $end
$var wire 1 1 init_done1 $end
$var wire 8 2 data_out_temp [7:0] $end
$var wire 8 3 data_out [7:0] $end
$var reg 8 4 data_out_temp2 [7:0] $end
$var reg 32 5 i [31:0] $end
$var reg 32 6 j [31:0] $end
$var reg 2 7 state1 [1:0] $end
$var reg 2 8 state2 [1:0] $end
$var reg 1 9 valid2 $end
$scope module decrypt_d $end
$var wire 1 " clk $end
$var wire 8 : data_in [7:0] $end
$var wire 1 ; done $end
$var wire 8 < password [7:0] $end
$var wire 1 ) rst $end
$var wire 1 9 valid $end
$var wire 1 = output_ready $end
$var wire 1 0 init_done $end
$var wire 8 > K [7:0] $end
$var reg 8 ? data_out [7:0] $end
$var reg 1 . out_valid $end
$var reg 8 @ temp_K [7:0] $end
$var reg 8 A temp_K2 [7:0] $end
$var reg 1 B temp_out_valid $end
$scope module device $end
$var wire 1 " clk $end
$var wire 1 0 init_done $end
$var wire 8 C password_input [7:0] $end
$var wire 1 ) rst $end
$var wire 1 D start $end
$var wire 1 9 valid $end
$var reg 8 E K [7:0] $end
$var reg 4 F KSState [3:0] $end
$var reg 10 G discardCount [9:0] $end
$var reg 8 H i [7:0] $end
$var reg 8 I j [7:0] $end
$var reg 8 J key [7:0] $end
$var reg 1 = output_ready $end
$var reg 8 K temp_K [7:0] $end
$var reg 8 L tmp [7:0] $end
$upscope $end
$upscope $end
$scope module encrypt_d $end
$var wire 1 " clk $end
$var wire 8 M data_in [7:0] $end
$var wire 8 N password [7:0] $end
$var wire 1 ) rst $end
$var wire 1 + valid $end
$var wire 1 O output_ready $end
$var wire 1 1 init_done $end
$var wire 8 P K [7:0] $end
$var reg 8 Q data_out [7:0] $end
$var reg 1 / out_valid $end
$var reg 8 R temp_K [7:0] $end
$scope module device $end
$var wire 1 " clk $end
$var wire 1 1 init_done $end
$var wire 8 S password_input [7:0] $end
$var wire 1 ) rst $end
$var wire 1 T start $end
$var wire 1 + valid $end
$var reg 8 U K [7:0] $end
$var reg 4 V KSState [3:0] $end
$var reg 10 W discardCount [9:0] $end
$var reg 8 X i [7:0] $end
$var reg 8 Y j [7:0] $end
$var reg 8 Z key [7:0] $end
$var reg 1 O output_ready $end
$var reg 8 [ temp_K [7:0] $end
$var reg 8 \ tmp [7:0] $end
$upscope $end
$upscope $end
$upscope $end
$upscope $end
$enddefinitions $end
#0
$dumpvars
bx \
bx [
bx Z
bx Y
bx X
bx W
b110 V
b0 U
zT
b0 S
b0 R
bx Q
b0 P
xO
b0 N
b0 M
bx L
bx K
bx J
bx I
bx H
bx G
b110 F
b0 E
zD
b0 C
0B
b0 A
b0 @
bx ?
b0 >
x=
b0 <
z;
b0 :
x9
b0 8
b0 7
b0 6
b0 5
b0 4
bx 3
bx 2
01
00
0/
0.
b0 -
b0 ,
0+
0*
1)
0(
0'
b0 &
0%
0$
b0 #
0"
bx !
$end
#5
b0 I
0=
b0 F
b0 H
b0 Y
0O
b0 V
b0 X
b0 2
b0 Q
b0 !
b0 3
b0 ?
09
1"
#10
b10100000 &
b10100000 -
b10100000 <
b10100000 C
b10100000 N
b10100000 S
0)
0"
#15
b10100000 [
b10100000 Z
b1 V
b10100000 K
b10100000 J
b1 F
b10100000 @
b10100000 R
1"
#20
0"
#25
b1 H
b1 X
1"
#30
0"
#35
b10 X
b10 H
1"
#40
0"
#45
b11 H
b11 X
1"
#50
0"
#55
b100 X
b100 H
1"
#60
0"
#65
b101 H
b101 X
1"
#70
0"
#75
b110 X
b110 H
1"
#80
0"
#85
b111 H
b111 X
1"
#90
0"
#95
b1000 X
b1000 H
1"
#100
0"
#105
b1001 H
b1001 X
1"
#110
0"
#115
b1010 X
b1010 H
1"
#120
0"
#125
b1011 H
b1011 X
1"
#130
0"
#135
b1100 X
b1100 H
1"
#140
0"
#145
b1101 H
b1101 X
1"
#150
0"
#155
b1110 X
b1110 H
1"
#160
0"
#165
b1111 H
b1111 X
1"
#170
0"
#175
b10000 X
b10000 H
1"
#180
0"
#185
b10001 H
b10001 X
1"
#190
0"
#195
b10010 X
b10010 H
1"
#200
0"
#205
b10011 H
b10011 X
1"
#210
0"
#215
b10100 X
b10100 H
1"
#220
0"
#225
b10101 H
b10101 X
1"
#230
0"
#235
b10110 X
b10110 H
1"
#240
0"
#245
b10111 H
b10111 X
1"
#250
0"
#255
b11000 X
b11000 H
1"
#260
0"
#265
b11001 H
b11001 X
1"
#270
0"
#275
b11010 X
b11010 H
1"
#280
0"
#285
b11011 H
b11011 X
1"
#290
0"
#295
b11100 X
b11100 H
1"
#300
0"
#305
b11101 H
b11101 X
1"
#310
0"
#315
b11110 X
b11110 H
1"
#320
0"
#325
b11111 H
b11111 X
1"
#330
0"
#335
b100000 X
b100000 H
1"
#340
0"
#345
b100001 H
b100001 X
1"
#350
0"
#355
b100010 X
b100010 H
1"
#360
0"
#365
b100011 H
b100011 X
1"
#370
0"
#375
b100100 X
b100100 H
1"
#380
0"
#385
b100101 H
b100101 X
1"
#390
0"
#395
b100110 X
b100110 H
1"
#400
0"
#405
b100111 H
b100111 X
1"
#410
0"
#415
b101000 X
b101000 H
1"
#420
0"
#425
b101001 H
b101001 X
1"
#430
0"
#435
b101010 X
b101010 H
1"
#440
0"
#445
b101011 H
b101011 X
1"
#450
0"
#455
b101100 X
b101100 H
1"
#460
0"
#465
b101101 H
b101101 X
1"
#470
0"
#475
b101110 X
b101110 H
1"
#480
0"
#485
b101111 H
b101111 X
1"
#490
0"
#495
b110000 X
b110000 H
1"
#500
0"
#505
b110001 H
b110001 X
1"
#510
0"
#515
b110010 X
b110010 H
1"
#520
0"
#525
b110011 H
b110011 X
1"
#530
0"
#535
b110100 X
b110100 H
1"
#540
0"
#545
b110101 H
b110101 X
1"
#550
0"
#555
b110110 X
b110110 H
1"
#560
0"
#565
b110111 H
b110111 X
1"
#570
0"
#575
b111000 X
b111000 H
1"
#580
0"
#585
b111001 H
b111001 X
1"
#590
0"
#595
b111010 X
b111010 H
1"
#600
0"
#605
b111011 H
b111011 X
1"
#610
0"
#615
b111100 X
b111100 H
1"
#620
0"
#625
b111101 H
b111101 X
1"
#630
0"
#635
b111110 X
b111110 H
1"
#640
0"
#645
b111111 H
b111111 X
1"
#650
0"
#655
b1000000 X
b1000000 H
1"
#660
0"
#665
b1000001 H
b1000001 X
1"
#670
0"
#675
b1000010 X
b1000010 H
1"
#680
0"
#685
b1000011 H
b1000011 X
1"
#690
0"
#695
b1000100 X
b1000100 H
1"
#700
0"
#705
b1000101 H
b1000101 X
1"
#710
0"
#715
b1000110 X
b1000110 H
1"
#720
0"
#725
b1000111 H
b1000111 X
1"
#730
0"
#735
b1001000 X
b1001000 H
1"
#740
0"
#745
b1001001 H
b1001001 X
1"
#750
0"
#755
b1001010 X
b1001010 H
1"
#760
0"
#765
b1001011 H
b1001011 X
1"
#770
0"
#775
b1001100 X
b1001100 H
1"
#780
0"
#785
b1001101 H
b1001101 X
1"
#790
0"
#795
b1001110 X
b1001110 H
1"
#800
0"
#805
b1001111 H
b1001111 X
1"
#810
0"
#815
b1010000 X
b1010000 H
1"
#820
0"
#825
b1010001 H
b1010001 X
1"
#830
0"
#835
b1010010 X
b1010010 H
1"
#840
0"
#845
b1010011 H
b1010011 X
1"
#850
0"
#855
b1010100 X
b1010100 H
1"
#860
0"
#865
b1010101 H
b1010101 X
1"
#870
0"
#875
b1010110 X
b1010110 H
1"
#880
0"
#885
b1010111 H
b1010111 X
1"
#890
0"
#895
b1011000 X
b1011000 H
1"
#900
0"
#905
b1011001 H
b1011001 X
1"
#910
0"
#915
b1011010 X
b1011010 H
1"
#920
0"
#925
b1011011 H
b1011011 X
1"
#930
0"
#935
b1011100 X
b1011100 H
1"
#940
0"
#945
b1011101 H
b1011101 X
1"
#950
0"
#955
b1011110 X
b1011110 H
1"
#960
0"
#965
b1011111 H
b1011111 X
1"
#970
0"
#975
b1100000 X
b1100000 H
1"
#980
0"
#985
b1100001 H
b1100001 X
1"
#990
0"
#995
b1100010 X
b1100010 H
1"
#1000
0"
#1005
b1100011 H
b1100011 X
1"
#1010
0"
#1015
b1100100 X
b1100100 H
1"
#1020
0"
#1025
b1100101 H
b1100101 X
1"
#1030
0"
#1035
b1100110 X
b1100110 H
1"
#1040
0"
#1045
b1100111 H
b1100111 X
1"
#1050
0"
#1055
b1101000 X
b1101000 H
1"
#1060
0"
#1065
b1101001 H
b1101001 X
1"
#1070
0"
#1075
b1101010 X
b1101010 H
1"
#1080
0"
#1085
b1101011 H
b1101011 X
1"
#1090
0"
#1095
b1101100 X
b1101100 H
1"
#1100
0"
#1105
b1101101 H
b1101101 X
1"
#1110
0"
#1115
b1101110 X
b1101110 H
1"
#1120
0"
#1125
b1101111 H
b1101111 X
1"
#1130
0"
#1135
b1110000 X
b1110000 H
1"
#1140
0"
#1145
b1110001 H
b1110001 X
1"
#1150
0"
#1155
b1110010 X
b1110010 H
1"
#1160
0"
#1165
b1110011 H
b1110011 X
1"
#1170
0"
#1175
b1110100 X
b1110100 H
1"
#1180
0"
#1185
b1110101 H
b1110101 X
1"
#1190
0"
#1195
b1110110 X
b1110110 H
1"
#1200
0"
#1205
b1110111 H
b1110111 X
1"
#1210
0"
#1215
b1111000 X
b1111000 H
1"
#1220
0"
#1225
b1111001 H
b1111001 X
1"
#1230
0"
#1235
b1111010 X
b1111010 H
1"
#1240
0"
#1245
b1111011 H
b1111011 X
1"
#1250
0"
#1255
b1111100 X
b1111100 H
1"
#1260
0"
#1265
b1111101 H
b1111101 X
1"
#1270
0"
#1275
b1111110 X
b1111110 H
1"
#1280
0"
#1285
b1111111 H
b1111111 X
1"
#1290
0"
#1295
b10000000 X
b10000000 H
1"
#1300
0"
#1305
b10000001 H
b10000001 X
1"
#1310
0"
#1315
b10000010 X
b10000010 H
1"
#1320
0"
#1325
b10000011 H
b10000011 X
1"
#1330
0"
#1335
b10000100 X
b10000100 H
1"
#1340
0"
#1345
b10000101 H
b10000101 X
1"
#1350
0"
#1355
b10000110 X
b10000110 H
1"
#1360
0"
#1365
b10000111 H
b10000111 X
1"
#1370
0"
#1375
b10001000 X
b10001000 H
1"
#1380
0"
#1385
b10001001 H
b10001001 X
1"
#1390
0"
#1395
b10001010 X
b10001010 H
1"
#1400
0"
#1405
b10001011 H
b10001011 X
1"
#1410
0"
#1415
b10001100 X
b10001100 H
1"
#1420
0"
#1425
b10001101 H
b10001101 X
1"
#1430
0"
#1435
b10001110 X
b10001110 H
1"
#1440
0"
#1445
b10001111 H
b10001111 X
1"
#1450
0"
#1455
b10010000 X
b10010000 H
1"
#1460
0"
#1465
b10010001 H
b10010001 X
1"
#1470
0"
#1475
b10010010 X
b10010010 H
1"
#1480
0"
#1485
b10010011 H
b10010011 X
1"
#1490
0"
#1495
b10010100 X
b10010100 H
1"
#1500
0"
#1505
b10010101 H
b10010101 X
1"
#1510
0"
#1515
b10010110 X
b10010110 H
1"
#1520
0"
#1525
b10010111 H
b10010111 X
1"
#1530
0"
#1535
b10011000 X
b10011000 H
1"
#1540
0"
#1545
b10011001 H
b10011001 X
1"
#1550
0"
#1555
b10011010 X
b10011010 H
1"
#1560
0"
#1565
b10011011 H
b10011011 X
1"
#1570
0"
#1575
b10011100 X
b10011100 H
1"
#1580
0"
#1585
b10011101 H
b10011101 X
1"
#1590
0"
#1595
b10011110 X
b10011110 H
1"
#1600
0"
#1605
b10011111 H
b10011111 X
1"
#1610
0"
#1615
b10100000 X
b10100000 H
1"
#1620
0"
#1625
b10100001 H
b10100001 X
1"
#1630
0"
#1635
b10100010 X
b10100010 H
1"
#1640
0"
#1645
b10100011 H
b10100011 X
1"
#1650
0"
#1655
b10100100 X
b10100100 H
1"
#1660
0"
#1665
b10100101 H
b10100101 X
1"
#1670
0"
#1675
b10100110 X
b10100110 H
1"
#1680
0"
#1685
b10100111 H
b10100111 X
1"
#1690
0"
#1695
b10101000 X
b10101000 H
1"
#1700
0"
#1705
b10101001 H
b10101001 X
1"
#1710
0"
#1715
b10101010 X
b10101010 H
1"
#1720
0"
#1725
b10101011 H
b10101011 X
1"
#1730
0"
#1735
b10101100 X
b10101100 H
1"
#1740
0"
#1745
b10101101 H
b10101101 X
1"
#1750
0"
#1755
b10101110 X
b10101110 H
1"
#1760
0"
#1765
b10101111 H
b10101111 X
1"
#1770
0"
#1775
b10110000 X
b10110000 H
1"
#1780
0"
#1785
b10110001 H
b10110001 X
1"
#1790
0"
#1795
b10110010 X
b10110010 H
1"
#1800
0"
#1805
b10110011 H
b10110011 X
1"
#1810
0"
#1815
b10110100 X
b10110100 H
1"
#1820
0"
#1825
b10110101 H
b10110101 X
1"
#1830
0"
#1835
b10110110 X
b10110110 H
1"
#1840
0"
#1845
b10110111 H
b10110111 X
1"
#1850
0"
#1855
b10111000 X
b10111000 H
1"
#1860
0"
#1865
b10111001 H
b10111001 X
1"
#1870
0"
#1875
b10111010 X
b10111010 H
1"
#1880
0"
#1885
b10111011 H
b10111011 X
1"
#1890
0"
#1895
b10111100 X
b10111100 H
1"
#1900
0"
#1905
b10111101 H
b10111101 X
1"
#1910
0"
#1915
b10111110 X
b10111110 H
1"
#1920
0"
#1925
b10111111 H
b10111111 X
1"
#1930
0"
#1935
b11000000 X
b11000000 H
1"
#1940
0"
#1945
b11000001 H
b11000001 X
1"
#1950
0"
#1955
b11000010 X
b11000010 H
1"
#1960
0"
#1965
b11000011 H
b11000011 X
1"
#1970
0"
#1975
b11000100 X
b11000100 H
1"
#1980
0"
#1985
b11000101 H
b11000101 X
1"
#1990
0"
#1995
b11000110 X
b11000110 H
1"
#2000
0"
#2005
b11000111 H
b11000111 X
1"
#2010
0"
#2015
b11001000 X
b11001000 H
1"
#2020
0"
#2025
b11001001 H
b11001001 X
1"
#2030
0"
#2035
b11001010 X
b11001010 H
1"
#2040
0"
#2045
b11001011 H
b11001011 X
1"
#2050
0"
#2055
b11001100 X
b11001100 H
1"
#2060
0"
#2065
b11001101 H
b11001101 X
1"
#2070
0"
#2075
b11001110 X
b11001110 H
1"
#2080
0"
#2085
b11001111 H
b11001111 X
1"
#2090
0"
#2095
b11010000 X
b11010000 H
1"
#2100
0"
#2105
b11010001 H
b11010001 X
1"
#2110
0"
#2115
b11010010 X
b11010010 H
1"
#2120
0"
#2125
b11010011 H
b11010011 X
1"
#2130
0"
#2135
b11010100 X
b11010100 H
1"
#2140
0"
#2145
b11010101 H
b11010101 X
1"
#2150
0"
#2155
b11010110 X
b11010110 H
1"
#2160
0"
#2165
b11010111 H
b11010111 X
1"
#2170
0"
#2175
b11011000 X
b11011000 H
1"
#2180
0"
#2185
b11011001 H
b11011001 X
1"
#2190
0"
#2195
b11011010 X
b11011010 H
1"
#2200
0"
#2205
b11011011 H
b11011011 X
1"
#2210
0"
#2215
b11011100 X
b11011100 H
1"
#2220
0"
#2225
b11011101 H
b11011101 X
1"
#2230
0"
#2235
b11011110 X
b11011110 H
1"
#2240
0"
#2245
b11011111 H
b11011111 X
1"
#2250
0"
#2255
b11100000 X
b11100000 H
1"
#2260
0"
#2265
b11100001 H
b11100001 X
1"
#2270
0"
#2275
b11100010 X
b11100010 H
1"
#2280
0"
#2285
b11100011 H
b11100011 X
1"
#2290
0"
#2295
b11100100 X
b11100100 H
1"
#2300
0"
#2305
b11100101 H
b11100101 X
1"
#2310
0"
#2315
b11100110 X
b11100110 H
1"
#2320
0"
#2325
b11100111 H
b11100111 X
1"
#2330
0"
#2335
b11101000 X
b11101000 H
1"
#2340
0"
#2345
b11101001 H
b11101001 X
1"
#2350
0"
#2355
b11101010 X
b11101010 H
1"
#2360
0"
#2365
b11101011 H
b11101011 X
1"
#2370
0"
#2375
b11101100 X
b11101100 H
1"
#2380
0"
#2385
b11101101 H
b11101101 X
1"
#2390
0"
#2395
b11101110 X
b11101110 H
1"
#2400
0"
#2405
b11101111 H
b11101111 X
1"
#2410
0"
#2415
b11110000 X
b11110000 H
1"
#2420
0"
#2425
b11110001 H
b11110001 X
1"
#2430
0"
#2435
b11110010 X
b11110010 H
1"
#2440
0"
#2445
b11110011 H
b11110011 X
1"
#2450
0"
#2455
b11110100 X
b11110100 H
1"
#2460
0"
#2465
b11110101 H
b11110101 X
1"
#2470
0"
#2475
b11110110 X
b11110110 H
1"
#2480
0"
#2485
b11110111 H
b11110111 X
1"
#2490
0"
#2495
b11111000 X
b11111000 H
1"
#2500
0"
#2505
b11111001 H
b11111001 X
1"
#2510
0"
#2515
b11111010 X
b11111010 H
1"
#2520
0"
#2525
b11111011 H
b11111011 X
1"
#2530
0"
#2535
b11111100 X
b11111100 H
1"
#2540
0"
#2545
b11111101 H
b11111101 X
1"
#2550
0"
#2555
b11111110 X
b11111110 H
1"
#2560
0"
#2565
b11111111 H
b11111111 X
1"
#2570
0"
#2575
b0 X
b10 V
b0 H
b10 F
1"
#2580
0"
#2585
b11 F
b11 V
1"
#2590
0"
#2595
b10 V
b1 X
b10 F
b1 H
1"
#2600
0"
#2605
b11 F
b1 I
b11 V
b1 Y
1"
#2610
0"
#2615
b10 V
b10 X
b10 F
b10 H
1"
#2620
0"
#2625
b11 F
b11 I
b11 V
b11 Y
1"
#2630
0"
#2635
b10 V
b11 X
b10 F
b11 H
1"
#2640
0"
#2645
b11 F
b101 I
b11 V
b101 Y
1"
#2650
0"
#2655
b10 V
b100 X
b10 F
b100 H
1"
#2660
0"
#2665
b11 F
b1001 I
b11 V
b1001 Y
1"
#2670
0"
#2675
b10 V
b101 X
b10 F
b101 H
1"
#2680
0"
#2685
b11 F
b1100 I
b11 V
b1100 Y
1"
#2690
0"
#2695
b10 V
b110 X
b10 F
b110 H
1"
#2700
0"
#2705
b11 F
b10010 I
b11 V
b10010 Y
1"
#2710
0"
#2715
b10 V
b111 X
b10 F
b111 H
1"
#2720
0"
#2725
b11 F
b11001 I
b11 V
b11001 Y
1"
#2730
0"
#2735
b10 V
b1000 X
b10 F
b1000 H
1"
#2740
0"
#2745
b11 F
b100001 I
b11 V
b100001 Y
1"
#2750
0"
#2755
b10 V
b1001 X
b10 F
b1001 H
1"
#2760
0"
#2765
b11 F
b100101 I
b11 V
b100101 Y
1"
#2770
0"
#2775
b10 V
b1010 X
b10 F
b1010 H
1"
#2780
0"
#2785
b11 F
b101111 I
b11 V
b101111 Y
1"
#2790
0"
#2795
b10 V
b1011 X
b10 F
b1011 H
1"
#2800
0"
#2805
b11 F
b111010 I
b11 V
b111010 Y
1"
#2810
0"
#2815
b10 V
b1100 X
b10 F
b1100 H
1"
#2820
0"
#2825
b11 F
b111101 I
b11 V
b111101 Y
1"
#2830
0"
#2835
b10 V
b1101 X
b10 F
b1101 H
1"
#2840
0"
#2845
b11 F
b1001010 I
b11 V
b1001010 Y
1"
#2850
0"
#2855
b10 V
b1110 X
b10 F
b1110 H
1"
#2860
0"
#2865
b11 F
b1011000 I
b11 V
b1011000 Y
1"
#2870
0"
#2875
b10 V
b1111 X
b10 F
b1111 H
1"
#2880
0"
#2885
b11 F
b1100111 I
b11 V
b1100111 Y
1"
#2890
0"
#2895
b10 V
b10000 X
b10 F
b10000 H
1"
#2900
0"
#2905
b11 F
b1110111 I
b11 V
b1110111 Y
1"
#2910
0"
#2915
b10 V
b10001 X
b10 F
b10001 H
1"
#2920
0"
#2925
b11 F
b10001000 I
b11 V
b10001000 Y
1"
#2930
0"
#2935
b10 V
b10010 X
b10 F
b10010 H
1"
#2940
0"
#2945
b11 F
b10001110 I
b11 V
b10001110 Y
1"
#2950
0"
#2955
b10 V
b10011 X
b10 F
b10011 H
1"
#2960
0"
#2965
b11 F
b10100010 I
b11 V
b10100010 Y
1"
#2970
0"
#2975
b10 V
b10100 X
b10 F
b10100 H
1"
#2980
0"
#2985
b11 F
b10110110 I
b11 V
b10110110 Y
1"
#2990
0"
#2995
b10 V
b10101 X
b10 F
b10101 H
1"
#3000
0"
#3005
b11 F
b11001011 I
b11 V
b11001011 Y
1"
#3010
0"
#3015
b10 V
b10110 X
b10 F
b10110 H
1"
